dabapush/Configuration/ConfigurationError.py
dabapush/Configuration/DBWriterConfiguration.py
dabapush/Configuration/FileWriterConfiguration.py
dabapush/Configuration/PlugInConfiguration.py
dabapush/Configuration/ProjectConfiguration.py
dabapush/Configuration/ReaderConfiguration.py
dabapush/Configuration/Registry.py
dabapush/Configuration/WriterConfiguration.py
dabapush/Configuration/__init__.py
dabapush/Dabapush.py
dabapush/Reader/NDJSONReader.py
dabapush/Reader/Reader.py
dabapush/Reader/TwacapicReader.py
dabapush/Reader/__init__.py
dabapush/Reader/tegracli_reader.py
dabapush/Writer/CSVWriter.py
dabapush/Writer/FacebookDBWriter.py
dabapush/Writer/InstagramDBWriter.py
dabapush/Writer/NDJSONWriter.py
dabapush/Writer/TelegramDBWriter.py
dabapush/Writer/TwitterDBWriter.py
dabapush/Writer/Writer.py
dabapush/Writer/__init__.py
dabapush/__init__.py
dabapush/create_subcommand.py
dabapush/main.py
dabapush/reader_subcommand.py
dabapush/run_subcommand.py
dabapush/update_subcommand.py
dabapush/utils.py
dabapush/writer_subcommand.py
smo-database/.git
smo-database/.gitignore
smo-database/LICENSE
smo-database/README.md
smo-database/__init__.py
smo-database/data/facebook/README.md
smo-database/data/instagram/1617823/111322/2021-11-10.ndjson
smo-database/data/instagram/1617823/111322/last_post_date.txt
smo-database/data/instagram/1617823/177607/2021-11-10.ndjson
smo-database/data/instagram/1617823/177607/last_db_filedate.txt
smo-database/data/instagram/1617823/177607/last_post_date.txt
smo-database/data/instagram/1617823/264177/2021-11-10.ndjson
smo-database/data/instagram/1617823/264177/last_post_date.txt
smo-database/data/instagram/1617823/264202/2021-10-25.ndjson
smo-database/data/instagram/1617823/264202/2021-11-10.ndjson
smo-database/data/instagram/1617823/264202/last_db_filedate.txt
smo-database/data/instagram/1617823/264202/last_post_date.txt
smo-database/data/instagram/1617823/264207/2021-10-25.ndjson
smo-database/data/instagram/1617823/264207/2021-11-10.ndjson
dabapush-0.3.3.dist-info/entry_points.txt
dabapush-0.3.3.dist-info/LICENSE
dabapush-0.3.3.dist-info/WHEEL
dabapush-0.3.3.dist-info/METADATA
dabapush-0.3.3.dist-info/RECORD
