Metadata-Version: 2.1
Name: dabapush
Version: 0.3.3
Summary: 
Home-page: https://github.com/Leibniz-HBI/dabapush
License: MIT
Author: Philipp Kessling
Author-email: p.kessling@leibniz-hbi.de
Requires-Python: >=3.8,<4.0
Classifier: Development Status :: 2 - Pre-Alpha
Classifier: Environment :: Console
Classifier: Intended Audience :: Science/Research
Classifier: License :: OSI Approved :: MIT License
Classifier: Programming Language :: Python :: 3
Classifier: Programming Language :: Python :: 3.10
Classifier: Programming Language :: Python :: 3.8
Classifier: Programming Language :: Python :: 3.9
Requires-Dist: PyYAML
Requires-Dist: SQLAlchemy
Requires-Dist: click
Requires-Dist: importlib-metadata
Requires-Dist: loguru
Requires-Dist: pandas
Requires-Dist: psycopg2-binary
Requires-Dist: ujson
Project-URL: Repository, https://github.com/Leibniz-HBI/dabapush
